{
  "doc-d5294a65ee262e174caff43c5149ab73": {
    "entity_names": [
      "Milton",
      "FREE",
      "THINKFUL",
      "HONOUR",
      "Fornication",
      "-WISE",
      "TAKEN",
      "Dickens",
      "Good",
      "Goodthinking",
      "SWAM",
      "Light",
      "GOOD",
      "MINTRU",
      "SPOKE",
      "B Vocabulary (compound words)",
      "Thinkpol",
      "Joycamp",
      "-ES",
      "GAVE",
      "Thought Police",
      "1984",
      "DEMOCRACY",
      "minipax",
      "MINIPAX",
      "BELLYFEEL",
      "INTERNATIONALISM",
      "Death Penalty",
      "UP-",
      "SPEEDFUL",
      "Oldspeak",
      "INGSOC PRINCIPLES",
      "Adultery",
      "Ingsoc Principles",
      "Prestige",
      "GOODTHINKWISE",
      "Technical Manuals",
      "thinkpol",
      "SCIENCE",
      "MORALITY",
      "-FUL",
      "B vocabulary",
      "absolute government",
      "Newspeak Words",
      "OX",
      "Ingsoc",
      "Newspeak Vocabulary",
      "INGSOC",
      "SPEEDWISE",
      "Ministry of Truth",
      "Fiction Department",
      "OLDTHINKING",
      "RELIGION",
      "Newspeak",
      "Shakespeare",
      "Records Department",
      "Winston Smith",
      "MINILOVEFUL",
      "Oceanic Society",
      "MINITRUTHFUL",
      "LIFE",
      "UNCOLD",
      "KNIFE",
      "GOODTHINKFUL",
      "SPEAKWRITE",
      "Certain Historical Figures",
      "AGITPROP",
      "Jefferson's words",
      "UNDARK",
      "Sexcrime",
      "preserved memory",
      "Minipax",
      "-S",
      "JUSTICE",
      "Party Members",
      "Oldthinking",
      "COMINTERN",
      "Byron",
      "Declaration of Independence",
      "GOODWISE",
      "Sexual Immorality",
      "Minilovely",
      "UNLIGHT",
      "C vocabulary",
      "Goodthink",
      "GOODTHINKED",
      "OLDTHINK",
      "GOODER",
      "Swift",
      "GESTAPO",
      "goodthinked",
      "minitrue",
      "PLUSCOLD",
      "UNGOOD",
      "MAN",
      "nineteen eighty-four",
      "C Vocabulary",
      "Teleprogrammes Department",
      "Minipeaceful",
      "ANTE-",
      "a good deal of the literature",
      "CRIMETHINK",
      "B Words",
      "Minitrue",
      "DoublePlusCold",
      "goodthinker",
      "-ED",
      "crimethink",
      "-ER,-EST",
      "Heretics",
      "Revolution",
      "NAZI",
      "GOOD-THINKING",
      "A Vocabulary",
      "GOODTHINKER",
      "GOODSEX",
      "GOODEST",
      "C VOCABULARY",
      "DUCKSPEAK",
      "WHOM",
      "Oldthinkers",
      "Thomas Jefferson",
      "Prolefeed",
      "THINKPOL",
      "Newspeak Dictionary",
      "MINISTRY OF TRUTH",
      "Big Brother",
      "OLDTHINKERS",
      "Jefferson",
      "Oceania",
      "Ings",
      "BROUGHT",
      "DOUBLEPLUSCOLD",
      "-S,-ES",
      "DOWN-",
      "SEXCRIME",
      "JOYCAMP",
      "The Times",
      "POST-",
      "THINK",
      "bellyfeel",
      "DARK",
      "Homosexuality",
      "Doublethink",
      "MINILUV",
      "THOUGHT",
      "COLD",
      "B Vocabulary"
    ],
    "count": 148,
    "create_time": 1781752447,
    "update_time": 1781752447,
    "_id": "doc-d5294a65ee262e174caff43c5149ab73"
  }
}